{
    "Name": "Solid Mechanics ",
    "ShortName":"Solid",
    "Models":
    {
	"equations":"Elasticity"
    },
    "Materials":
    {
        "omega":
        {
            "E":"210e3",		// N/mm^2
            "nu":"0.4",			//
            "rho":"7800e-9"		// kg/mm^3
        }
    },
    "BoundaryConditions":
    {
        "displacement":
        {
            "Dirichlet":
            {
                "fixed":
                {
                    "expr":"{0,0,0}"
                }
            },
            "Neumann_scalar":
            {
                "load":
                {
                    "expr":"1e0"
                }
            }
        }
    },
    "PostProcess":
    {
	"Exports":
	{
            "fields":["displacement","Von-Mises","tresca","principal-stresses"]
	},
        "Measures":
        {
	    "VolumeVariation":"omega",
	    "Maximum":
	    {
		"load":
		{
		    "markers":"load",
		    "fields":["displacement"]
		}
	    }            
        }
    }

}
